Serialization/__init__.py
Serialization/base_serializer.py
Serialization/dict_serializer.py
Serialization/json_serializer.py
Serialization/serializers_factory.py
Serialization/type_constants.py
Serialization/xml_serializer.py
GaikevichSerialization-0.1.1.dist-info/METADATA
GaikevichSerialization-0.1.1.dist-info/WHEEL
GaikevichSerialization-0.1.1.dist-info/top_level.txt
GaikevichSerialization-0.1.1.dist-info/RECORD
