Metadata-Version: 2.1
Name: GaikevichSerialization
Version: 0.1.1
Summary: Library for class and function serialization
Author: Egor Gaikevich
Author-email: egaikevich@yahoo.com
License: MIT
Classifier: Intended Audience :: Developers
Classifier: License :: OSI Approved :: MIT License
Classifier: Programming Language :: Python :: 3.10
Classifier: Operating System :: OS Independent
Requires-Dist: regex
